delegate/events/__init__.py
delegate/events/core/channel.py
delegate/events/core/channel_closed_error.py
delegate/events/core/event.py
delegate/events/core/handler_already_subscribed_error.py
delegate/events/core/handler_not_subscribed_error.py
delegate/events/core/queued_event.py
delegate_events-0.0.1.dist-info/licenses/LICENSE
delegate_events-0.0.1.dist-info/METADATA
delegate_events-0.0.1.dist-info/WHEEL
delegate_events-0.0.1.dist-info/top_level.txt
delegate_events-0.0.1.dist-info/RECORD
